[
  [
    "_metadata",
    {
      "jsonVersion": 3,
      "className": "ReferenceChemicalShift",
      "classVersion": 1,
      "user": "CCPN",
      "lastPath": "/Users/luca/Projects/AnalysisV3/resources/referenceChemicalShifts/NonStandard/Non-Polymer/C2E.json",
      "timestamp": "Tue Jan  9 15:18:19 2024",
      "applicationVersion": 3.2
    }
  ],
  [
    "chemicalShiftName",
    "Non-Standard Residues / Small Molecules"
  ],
  [
    "chemicalShiftComment",
    "The CCPN Analysis Version 3 ReferenceChemical shifts retrieved from BMRB"
  ],
  [
    "chemicalShiftEntryDate",
    "2023-09-14-14:25:08"
  ],
  [
    "compoundName",
    "9,9'-[(2R,3R,3aS,5S,7aR,9R,10R,10aS,12S,14aR)-3,5,10,12-tetrahydroxy-5,12-dioxidooctahydro-2H,7H-difuro[3,2-d:3',2'-j][1,3,7,9,2,8]tetraoxadiphosphacyclododecine-2,9-diyl]bis(2-amino-1,9-dihydro-6H-purin-6-one)"
  ],
  [
    "compoundShortName",
    "C2E"
  ],
  [
    "compoundCcpCode",
    "C2E"
  ],
  [
    "compoundType",
    "Non-Polymer"
  ],
  [
    "compoundTypeClassification",
    "non-polymer"
  ],
  [
    "compoundPrecursorName",
    ""
  ],
  [
    "loadingLevel",
    0
  ],
  [
    "atoms",
    [
      [
        [
          "_metadata",
          {
            "jsonVersion": 3.0,
            "className": "AtomChemicalShift",
            "classVersion": 1.0,
            "user": "luca",
            "lastPath": "undefined",
            "timestamp": "Tue Jan  9 15:18:19 2024"
          }
        ],
        [
          "atomName",
          "C1'"
        ],
        [
          "atomElementName",
          ""
        ],
        [
          "atomAverageShift",
          91.947
        ],
        [
          "atomStdShift",
          1.204
        ],
        [
          "atomMinShift",
          90.973
        ],
        [
          "atomMaxShift",
          93.65
        ],
        [
          "atomDistributionRefValue",
          90.973
        ],
        [
          "atomDistributionValuePerPoint",
          1.0
        ],
        [
          "atomStatisticalDistribution",
          []
        ]
      ],
      [
        [
          "_metadata",
          {
            "jsonVersion": 3.0,
            "className": "AtomChemicalShift",
            "classVersion": 1.0,
            "user": "luca",
            "lastPath": "undefined",
            "timestamp": "Tue Jan  9 15:18:19 2024"
          }
        ],
        [
          "atomName",
          "C1A"
        ],
        [
          "atomElementName",
          ""
        ],
        [
          "atomAverageShift",
          93.163
        ],
        [
          "atomStdShift",
          0.868
        ],
        [
          "atomMinShift",
          92.549
        ],
        [
          "atomMaxShift",
          93.777
        ],
        [
          "atomDistributionRefValue",
          92.549
        ],
        [
          "atomDistributionValuePerPoint",
          1.0
        ],
        [
          "atomStatisticalDistribution",
          []
        ]
      ],
      [
        [
          "_metadata",
          {
            "jsonVersion": 3.0,
            "className": "AtomChemicalShift",
            "classVersion": 1.0,
            "user": "luca",
            "lastPath": "undefined",
            "timestamp": "Tue Jan  9 15:18:19 2024"
          }
        ],
        [
          "atomName",
          "C2'"
        ],
        [
          "atomElementName",
          ""
        ],
        [
          "atomAverageShift",
          76.952
        ],
        [
          "atomStdShift",
          0.722
        ],
        [
          "atomMinShift",
          76.051
        ],
        [
          "atomMaxShift",
          77.783
        ],
        [
          "atomDistributionRefValue",
          76.051
        ],
        [
          "atomDistributionValuePerPoint",
          1.0
        ],
        [
          "atomStatisticalDistribution",
          []
        ]
      ],
      [
        [
          "_metadata",
          {
            "jsonVersion": 3.0,
            "className": "AtomChemicalShift",
            "classVersion": 1.0,
            "user": "luca",
            "lastPath": "undefined",
            "timestamp": "Tue Jan  9 15:18:19 2024"
          }
        ],
        [
          "atomName",
          "C2A"
        ],
        [
          "atomElementName",
          ""
        ],
        [
          "atomAverageShift",
          76.15
        ],
        [
          "atomStdShift",
          0.522
        ],
        [
          "atomMinShift",
          75.781
        ],
        [
          "atomMaxShift",
          76.519
        ],
        [
          "atomDistributionRefValue",
          75.781
        ],
        [
          "atomDistributionValuePerPoint",
          1.0
        ],
        [
          "atomStatisticalDistribution",
          []
        ]
      ],
      [
        [
          "_metadata",
          {
            "jsonVersion": 3.0,
            "className": "AtomChemicalShift",
            "classVersion": 1.0,
            "user": "luca",
            "lastPath": "undefined",
            "timestamp": "Tue Jan  9 15:18:19 2024"
          }
        ],
        [
          "atomName",
          "C3'"
        ],
        [
          "atomElementName",
          ""
        ],
        [
          "atomAverageShift",
          72.764
        ],
        [
          "atomStdShift",
          1.507
        ],
        [
          "atomMinShift",
          71.068
        ],
        [
          "atomMaxShift",
          74.046
        ],
        [
          "atomDistributionRefValue",
          71.068
        ],
        [
          "atomDistributionValuePerPoint",
          1.0
        ],
        [
          "atomStatisticalDistribution",
          []
        ]
      ],
      [
        [
          "_metadata",
          {
            "jsonVersion": 3.0,
            "className": "AtomChemicalShift",
            "classVersion": 1.0,
            "user": "luca",
            "lastPath": "undefined",
            "timestamp": "Tue Jan  9 15:18:19 2024"
          }
        ],
        [
          "atomName",
          "C3A"
        ],
        [
          "atomElementName",
          ""
        ],
        [
          "atomAverageShift",
          72.271
        ],
        [
          "atomStdShift",
          0.028
        ],
        [
          "atomMinShift",
          72.251
        ],
        [
          "atomMaxShift",
          72.29
        ],
        [
          "atomDistributionRefValue",
          72.251
        ],
        [
          "atomDistributionValuePerPoint",
          1.0
        ],
        [
          "atomStatisticalDistribution",
          []
        ]
      ],
      [
        [
          "_metadata",
          {
            "jsonVersion": 3.0,
            "className": "AtomChemicalShift",
            "classVersion": 1.0,
            "user": "luca",
            "lastPath": "undefined",
            "timestamp": "Tue Jan  9 15:18:19 2024"
          }
        ],
        [
          "atomName",
          "C4'"
        ],
        [
          "atomElementName",
          ""
        ],
        [
          "atomAverageShift",
          83.199
        ],
        [
          "atomStdShift",
          1.166
        ],
        [
          "atomMinShift",
          81.54
        ],
        [
          "atomMaxShift",
          84.078
        ],
        [
          "atomDistributionRefValue",
          81.54
        ],
        [
          "atomDistributionValuePerPoint",
          1.0
        ],
        [
          "atomStatisticalDistribution",
          []
        ]
      ],
      [
        [
          "_metadata",
          {
            "jsonVersion": 3.0,
            "className": "AtomChemicalShift",
            "classVersion": 1.0,
            "user": "luca",
            "lastPath": "undefined",
            "timestamp": "Tue Jan  9 15:18:19 2024"
          }
        ],
        [
          "atomName",
          "C4A"
        ],
        [
          "atomElementName",
          ""
        ],
        [
          "atomAverageShift",
          82.814
        ],
        [
          "atomStdShift",
          0.16
        ],
        [
          "atomMinShift",
          82.701
        ],
        [
          "atomMaxShift",
          82.927
        ],
        [
          "atomDistributionRefValue",
          82.701
        ],
        [
          "atomDistributionValuePerPoint",
          1.0
        ],
        [
          "atomStatisticalDistribution",
          []
        ]
      ],
      [
        [
          "_metadata",
          {
            "jsonVersion": 3.0,
            "className": "AtomChemicalShift",
            "classVersion": 1.0,
            "user": "luca",
            "lastPath": "undefined",
            "timestamp": "Tue Jan  9 15:18:19 2024"
          }
        ],
        [
          "atomName",
          "C5'"
        ],
        [
          "atomElementName",
          ""
        ],
        [
          "atomAverageShift",
          65.298
        ],
        [
          "atomStdShift",
          1.057
        ],
        [
          "atomMinShift",
          64.099
        ],
        [
          "atomMaxShift",
          66.096
        ],
        [
          "atomDistributionRefValue",
          64.099
        ],
        [
          "atomDistributionValuePerPoint",
          1.0
        ],
        [
          "atomStatisticalDistribution",
          []
        ]
      ],
      [
        [
          "_metadata",
          {
            "jsonVersion": 3.0,
            "className": "AtomChemicalShift",
            "classVersion": 1.0,
            "user": "luca",
            "lastPath": "undefined",
            "timestamp": "Tue Jan  9 15:18:19 2024"
          }
        ],
        [
          "atomName",
          "C5A"
        ],
        [
          "atomElementName",
          ""
        ],
        [
          "atomAverageShift",
          64.67
        ],
        [
          "atomStdShift",
          0.052
        ],
        [
          "atomMinShift",
          64.633
        ],
        [
          "atomMaxShift",
          64.706
        ],
        [
          "atomDistributionRefValue",
          64.633
        ],
        [
          "atomDistributionValuePerPoint",
          1.0
        ],
        [
          "atomStatisticalDistribution",
          []
        ]
      ],
      [
        [
          "_metadata",
          {
            "jsonVersion": 3.0,
            "className": "AtomChemicalShift",
            "classVersion": 1.0,
            "user": "luca",
            "lastPath": "undefined",
            "timestamp": "Tue Jan  9 15:18:19 2024"
          }
        ],
        [
          "atomName",
          "C8"
        ],
        [
          "atomElementName",
          ""
        ],
        [
          "atomAverageShift",
          137.456
        ],
        [
          "atomStdShift",
          0.429
        ],
        [
          "atomMinShift",
          137.152
        ],
        [
          "atomMaxShift",
          137.759
        ],
        [
          "atomDistributionRefValue",
          137.152
        ],
        [
          "atomDistributionValuePerPoint",
          1.0
        ],
        [
          "atomStatisticalDistribution",
          []
        ]
      ],
      [
        [
          "_metadata",
          {
            "jsonVersion": 3.0,
            "className": "AtomChemicalShift",
            "classVersion": 1.0,
            "user": "luca",
            "lastPath": "undefined",
            "timestamp": "Tue Jan  9 15:18:19 2024"
          }
        ],
        [
          "atomName",
          "H1'"
        ],
        [
          "atomElementName",
          ""
        ],
        [
          "atomAverageShift",
          5.433
        ],
        [
          "atomStdShift",
          1.109
        ],
        [
          "atomMinShift",
          3.289
        ],
        [
          "atomMaxShift",
          6.211
        ],
        [
          "atomDistributionRefValue",
          3.289
        ],
        [
          "atomDistributionValuePerPoint",
          1.0
        ],
        [
          "atomStatisticalDistribution",
          []
        ]
      ],
      [
        [
          "_metadata",
          {
            "jsonVersion": 3.0,
            "className": "AtomChemicalShift",
            "classVersion": 1.0,
            "user": "luca",
            "lastPath": "undefined",
            "timestamp": "Tue Jan  9 15:18:19 2024"
          }
        ],
        [
          "atomName",
          "H1A"
        ],
        [
          "atomElementName",
          ""
        ],
        [
          "atomAverageShift",
          5.367
        ],
        [
          "atomStdShift",
          0.344
        ],
        [
          "atomMinShift",
          4.88
        ],
        [
          "atomMaxShift",
          5.659
        ],
        [
          "atomDistributionRefValue",
          4.88
        ],
        [
          "atomDistributionValuePerPoint",
          1.0
        ],
        [
          "atomStatisticalDistribution",
          []
        ]
      ],
      [
        [
          "_metadata",
          {
            "jsonVersion": 3.0,
            "className": "AtomChemicalShift",
            "classVersion": 1.0,
            "user": "luca",
            "lastPath": "undefined",
            "timestamp": "Tue Jan  9 15:18:19 2024"
          }
        ],
        [
          "atomName",
          "H2'"
        ],
        [
          "atomElementName",
          ""
        ],
        [
          "atomAverageShift",
          4.569
        ],
        [
          "atomStdShift",
          0.367
        ],
        [
          "atomMinShift",
          3.953
        ],
        [
          "atomMaxShift",
          4.9
        ],
        [
          "atomDistributionRefValue",
          3.953
        ],
        [
          "atomDistributionValuePerPoint",
          1.0
        ],
        [
          "atomStatisticalDistribution",
          []
        ]
      ],
      [
        [
          "_metadata",
          {
            "jsonVersion": 3.0,
            "className": "AtomChemicalShift",
            "classVersion": 1.0,
            "user": "luca",
            "lastPath": "undefined",
            "timestamp": "Tue Jan  9 15:18:19 2024"
          }
        ],
        [
          "atomName",
          "H2A"
        ],
        [
          "atomElementName",
          ""
        ],
        [
          "atomAverageShift",
          4.945
        ],
        [
          "atomStdShift",
          0.665
        ],
        [
          "atomMinShift",
          4.473
        ],
        [
          "atomMaxShift",
          5.918
        ],
        [
          "atomDistributionRefValue",
          4.473
        ],
        [
          "atomDistributionValuePerPoint",
          1.0
        ],
        [
          "atomStatisticalDistribution",
          []
        ]
      ],
      [
        [
          "_metadata",
          {
            "jsonVersion": 3.0,
            "className": "AtomChemicalShift",
            "classVersion": 1.0,
            "user": "luca",
            "lastPath": "undefined",
            "timestamp": "Tue Jan  9 15:18:19 2024"
          }
        ],
        [
          "atomName",
          "H3'"
        ],
        [
          "atomElementName",
          ""
        ],
        [
          "atomAverageShift",
          4.866
        ],
        [
          "atomStdShift",
          0.327
        ],
        [
          "atomMinShift",
          4.437
        ],
        [
          "atomMaxShift",
          5.199
        ],
        [
          "atomDistributionRefValue",
          4.437
        ],
        [
          "atomDistributionValuePerPoint",
          1.0
        ],
        [
          "atomStatisticalDistribution",
          []
        ]
      ],
      [
        [
          "_metadata",
          {
            "jsonVersion": 3.0,
            "className": "AtomChemicalShift",
            "classVersion": 1.0,
            "user": "luca",
            "lastPath": "undefined",
            "timestamp": "Tue Jan  9 15:18:19 2024"
          }
        ],
        [
          "atomName",
          "H3A"
        ],
        [
          "atomElementName",
          ""
        ],
        [
          "atomAverageShift",
          4.735
        ],
        [
          "atomStdShift",
          0.167
        ],
        [
          "atomMinShift",
          4.59
        ],
        [
          "atomMaxShift",
          4.948
        ],
        [
          "atomDistributionRefValue",
          4.59
        ],
        [
          "atomDistributionValuePerPoint",
          1.0
        ],
        [
          "atomStatisticalDistribution",
          []
        ]
      ],
      [
        [
          "_metadata",
          {
            "jsonVersion": 3.0,
            "className": "AtomChemicalShift",
            "classVersion": 1.0,
            "user": "luca",
            "lastPath": "undefined",
            "timestamp": "Tue Jan  9 15:18:19 2024"
          }
        ],
        [
          "atomName",
          "H4'"
        ],
        [
          "atomElementName",
          ""
        ],
        [
          "atomAverageShift",
          4.373
        ],
        [
          "atomStdShift",
          0.16
        ],
        [
          "atomMinShift",
          4.087
        ],
        [
          "atomMaxShift",
          4.497
        ],
        [
          "atomDistributionRefValue",
          4.087
        ],
        [
          "atomDistributionValuePerPoint",
          1.0
        ],
        [
          "atomStatisticalDistribution",
          []
        ]
      ],
      [
        [
          "_metadata",
          {
            "jsonVersion": 3.0,
            "className": "AtomChemicalShift",
            "classVersion": 1.0,
            "user": "luca",
            "lastPath": "undefined",
            "timestamp": "Tue Jan  9 15:18:19 2024"
          }
        ],
        [
          "atomName",
          "H4A"
        ],
        [
          "atomElementName",
          ""
        ],
        [
          "atomAverageShift",
          4.355
        ],
        [
          "atomStdShift",
          0.021
        ],
        [
          "atomMinShift",
          4.325
        ],
        [
          "atomMaxShift",
          4.375
        ],
        [
          "atomDistributionRefValue",
          4.325
        ],
        [
          "atomDistributionValuePerPoint",
          1.0
        ],
        [
          "atomStatisticalDistribution",
          []
        ]
      ],
      [
        [
          "_metadata",
          {
            "jsonVersion": 3.0,
            "className": "AtomChemicalShift",
            "classVersion": 1.0,
            "user": "luca",
            "lastPath": "undefined",
            "timestamp": "Tue Jan  9 15:18:19 2024"
          }
        ],
        [
          "atomName",
          "H5'1"
        ],
        [
          "atomElementName",
          ""
        ],
        [
          "atomAverageShift",
          4.136
        ],
        [
          "atomStdShift",
          0.132
        ],
        [
          "atomMinShift",
          3.994
        ],
        [
          "atomMaxShift",
          4.314
        ],
        [
          "atomDistributionRefValue",
          3.994
        ],
        [
          "atomDistributionValuePerPoint",
          1.0
        ],
        [
          "atomStatisticalDistribution",
          []
        ]
      ],
      [
        [
          "_metadata",
          {
            "jsonVersion": 3.0,
            "className": "AtomChemicalShift",
            "classVersion": 1.0,
            "user": "luca",
            "lastPath": "undefined",
            "timestamp": "Tue Jan  9 15:18:19 2024"
          }
        ],
        [
          "atomName",
          "H5'2"
        ],
        [
          "atomElementName",
          ""
        ],
        [
          "atomAverageShift",
          4.336
        ],
        [
          "atomStdShift",
          0.428
        ],
        [
          "atomMinShift",
          3.853
        ],
        [
          "atomMaxShift",
          4.667
        ],
        [
          "atomDistributionRefValue",
          3.853
        ],
        [
          "atomDistributionValuePerPoint",
          1.0
        ],
        [
          "atomStatisticalDistribution",
          []
        ]
      ],
      [
        [
          "_metadata",
          {
            "jsonVersion": 3.0,
            "className": "AtomChemicalShift",
            "classVersion": 1.0,
            "user": "luca",
            "lastPath": "undefined",
            "timestamp": "Tue Jan  9 15:18:19 2024"
          }
        ],
        [
          "atomName",
          "H511"
        ],
        [
          "atomElementName",
          ""
        ],
        [
          "atomAverageShift",
          4.121
        ],
        [
          "atomStdShift",
          0.187
        ],
        [
          "atomMinShift",
          3.934
        ],
        [
          "atomMaxShift",
          4.381
        ],
        [
          "atomDistributionRefValue",
          3.934
        ],
        [
          "atomDistributionValuePerPoint",
          1.0
        ],
        [
          "atomStatisticalDistribution",
          []
        ]
      ],
      [
        [
          "_metadata",
          {
            "jsonVersion": 3.0,
            "className": "AtomChemicalShift",
            "classVersion": 1.0,
            "user": "luca",
            "lastPath": "undefined",
            "timestamp": "Tue Jan  9 15:18:19 2024"
          }
        ],
        [
          "atomName",
          "H512"
        ],
        [
          "atomElementName",
          ""
        ],
        [
          "atomAverageShift",
          4.405
        ],
        [
          "atomStdShift",
          0.276
        ],
        [
          "atomMinShift",
          4.12
        ],
        [
          "atomMaxShift",
          4.672
        ],
        [
          "atomDistributionRefValue",
          4.12
        ],
        [
          "atomDistributionValuePerPoint",
          1.0
        ],
        [
          "atomStatisticalDistribution",
          []
        ]
      ],
      [
        [
          "_metadata",
          {
            "jsonVersion": 3.0,
            "className": "AtomChemicalShift",
            "classVersion": 1.0,
            "user": "luca",
            "lastPath": "undefined",
            "timestamp": "Tue Jan  9 15:18:19 2024"
          }
        ],
        [
          "atomName",
          "H8"
        ],
        [
          "atomElementName",
          ""
        ],
        [
          "atomAverageShift",
          7.508
        ],
        [
          "atomStdShift",
          0.178
        ],
        [
          "atomMinShift",
          7.221
        ],
        [
          "atomMaxShift",
          7.658
        ],
        [
          "atomDistributionRefValue",
          7.221
        ],
        [
          "atomDistributionValuePerPoint",
          1.0
        ],
        [
          "atomStatisticalDistribution",
          []
        ]
      ],
      [
        [
          "_metadata",
          {
            "jsonVersion": 3.0,
            "className": "AtomChemicalShift",
            "classVersion": 1.0,
            "user": "luca",
            "lastPath": "undefined",
            "timestamp": "Tue Jan  9 15:18:19 2024"
          }
        ],
        [
          "atomName",
          "H81"
        ],
        [
          "atomElementName",
          ""
        ],
        [
          "atomAverageShift",
          7.479
        ],
        [
          "atomStdShift",
          0.091
        ],
        [
          "atomMinShift",
          7.368
        ],
        [
          "atomMaxShift",
          7.579
        ],
        [
          "atomDistributionRefValue",
          7.368
        ],
        [
          "atomDistributionValuePerPoint",
          1.0
        ],
        [
          "atomStatisticalDistribution",
          []
        ]
      ],
      [
        [
          "_metadata",
          {
            "jsonVersion": 3.0,
            "className": "AtomChemicalShift",
            "classVersion": 1.0,
            "user": "luca",
            "lastPath": "undefined",
            "timestamp": "Tue Jan  9 15:18:19 2024"
          }
        ],
        [
          "atomName",
          "HN1"
        ],
        [
          "atomElementName",
          ""
        ],
        [
          "atomAverageShift",
          11.688
        ],
        [
          "atomStdShift",
          0.369
        ],
        [
          "atomMinShift",
          11.148
        ],
        [
          "atomMaxShift",
          11.97
        ],
        [
          "atomDistributionRefValue",
          11.148
        ],
        [
          "atomDistributionValuePerPoint",
          1.0
        ],
        [
          "atomStatisticalDistribution",
          []
        ]
      ],
      [
        [
          "_metadata",
          {
            "jsonVersion": 3.0,
            "className": "AtomChemicalShift",
            "classVersion": 1.0,
            "user": "luca",
            "lastPath": "undefined",
            "timestamp": "Tue Jan  9 15:18:19 2024"
          }
        ],
        [
          "atomName",
          "HN11"
        ],
        [
          "atomElementName",
          ""
        ],
        [
          "atomAverageShift",
          12.265
        ],
        [
          "atomStdShift",
          1.282
        ],
        [
          "atomMinShift",
          10.767
        ],
        [
          "atomMaxShift",
          13.445
        ],
        [
          "atomDistributionRefValue",
          10.767
        ],
        [
          "atomDistributionValuePerPoint",
          1.0
        ],
        [
          "atomStatisticalDistribution",
          []
        ]
      ],
      [
        [
          "_metadata",
          {
            "jsonVersion": 3.0,
            "className": "AtomChemicalShift",
            "classVersion": 1.0,
            "user": "luca",
            "lastPath": "undefined",
            "timestamp": "Tue Jan  9 15:18:19 2024"
          }
        ],
        [
          "atomName",
          "HN21"
        ],
        [
          "atomElementName",
          ""
        ],
        [
          "atomAverageShift",
          5.884
        ],
        [
          "atomStdShift",
          0.364
        ],
        [
          "atomMinShift",
          5.537
        ],
        [
          "atomMaxShift",
          6.263
        ],
        [
          "atomDistributionRefValue",
          5.537
        ],
        [
          "atomDistributionValuePerPoint",
          1.0
        ],
        [
          "atomStatisticalDistribution",
          []
        ]
      ],
      [
        [
          "_metadata",
          {
            "jsonVersion": 3.0,
            "className": "AtomChemicalShift",
            "classVersion": 1.0,
            "user": "luca",
            "lastPath": "undefined",
            "timestamp": "Tue Jan  9 15:18:19 2024"
          }
        ],
        [
          "atomName",
          "HN23"
        ],
        [
          "atomElementName",
          ""
        ],
        [
          "atomAverageShift",
          5.849
        ],
        [
          "atomStdShift",
          0.214
        ],
        [
          "atomMinShift",
          5.698
        ],
        [
          "atomMaxShift",
          6.0
        ],
        [
          "atomDistributionRefValue",
          5.698
        ],
        [
          "atomDistributionValuePerPoint",
          1.0
        ],
        [
          "atomStatisticalDistribution",
          []
        ]
      ],
      [
        [
          "_metadata",
          {
            "jsonVersion": 3.0,
            "className": "AtomChemicalShift",
            "classVersion": 1.0,
            "user": "luca",
            "lastPath": "undefined",
            "timestamp": "Tue Jan  9 15:18:19 2024"
          }
        ],
        [
          "atomName",
          "N1"
        ],
        [
          "atomElementName",
          ""
        ],
        [
          "atomAverageShift",
          147.443
        ],
        [
          "atomStdShift",
          0.512
        ],
        [
          "atomMinShift",
          147.081
        ],
        [
          "atomMaxShift",
          147.805
        ],
        [
          "atomDistributionRefValue",
          147.081
        ],
        [
          "atomDistributionValuePerPoint",
          1.0
        ],
        [
          "atomStatisticalDistribution",
          []
        ]
      ],
      [
        [
          "_metadata",
          {
            "jsonVersion": 3.0,
            "className": "AtomChemicalShift",
            "classVersion": 1.0,
            "user": "luca",
            "lastPath": "undefined",
            "timestamp": "Tue Jan  9 15:18:19 2024"
          }
        ],
        [
          "atomName",
          "N11"
        ],
        [
          "atomElementName",
          ""
        ],
        [
          "atomAverageShift",
          145.614
        ],
        [
          "atomStdShift",
          null
        ],
        [
          "atomMinShift",
          145.614
        ],
        [
          "atomMaxShift",
          145.614
        ],
        [
          "atomDistributionRefValue",
          145.614
        ],
        [
          "atomDistributionValuePerPoint",
          1.0
        ],
        [
          "atomStatisticalDistribution",
          []
        ]
      ],
      [
        [
          "_metadata",
          {
            "jsonVersion": 3.0,
            "className": "AtomChemicalShift",
            "classVersion": 1.0,
            "user": "luca",
            "lastPath": "undefined",
            "timestamp": "Tue Jan  9 15:18:19 2024"
          }
        ],
        [
          "atomName",
          "N2"
        ],
        [
          "atomElementName",
          ""
        ],
        [
          "atomAverageShift",
          69.534
        ],
        [
          "atomStdShift",
          null
        ],
        [
          "atomMinShift",
          69.534
        ],
        [
          "atomMaxShift",
          69.534
        ],
        [
          "atomDistributionRefValue",
          69.534
        ],
        [
          "atomDistributionValuePerPoint",
          1.0
        ],
        [
          "atomStatisticalDistribution",
          []
        ]
      ],
      [
        [
          "_metadata",
          {
            "jsonVersion": 3.0,
            "className": "AtomChemicalShift",
            "classVersion": 1.0,
            "user": "luca",
            "lastPath": "undefined",
            "timestamp": "Tue Jan  9 15:18:19 2024"
          }
        ],
        [
          "atomName",
          "N21"
        ],
        [
          "atomElementName",
          ""
        ],
        [
          "atomAverageShift",
          69.824
        ],
        [
          "atomStdShift",
          null
        ],
        [
          "atomMinShift",
          69.824
        ],
        [
          "atomMaxShift",
          69.824
        ],
        [
          "atomDistributionRefValue",
          69.824
        ],
        [
          "atomDistributionValuePerPoint",
          1.0
        ],
        [
          "atomStatisticalDistribution",
          []
        ]
      ],
      [
        [
          "_metadata",
          {
            "jsonVersion": 3.0,
            "className": "AtomChemicalShift",
            "classVersion": 1.0,
            "user": "luca",
            "lastPath": "undefined",
            "timestamp": "Tue Jan  9 15:18:19 2024"
          }
        ],
        [
          "atomName",
          "N7"
        ],
        [
          "atomElementName",
          ""
        ],
        [
          "atomAverageShift",
          233.428
        ],
        [
          "atomStdShift",
          1.884
        ],
        [
          "atomMinShift",
          232.095
        ],
        [
          "atomMaxShift",
          234.76
        ],
        [
          "atomDistributionRefValue",
          232.095
        ],
        [
          "atomDistributionValuePerPoint",
          1.0
        ],
        [
          "atomStatisticalDistribution",
          []
        ]
      ],
      [
        [
          "_metadata",
          {
            "jsonVersion": 3.0,
            "className": "AtomChemicalShift",
            "classVersion": 1.0,
            "user": "luca",
            "lastPath": "undefined",
            "timestamp": "Tue Jan  9 15:18:19 2024"
          }
        ],
        [
          "atomName",
          "N71"
        ],
        [
          "atomElementName",
          ""
        ],
        [
          "atomAverageShift",
          231.818
        ],
        [
          "atomStdShift",
          4.913
        ],
        [
          "atomMinShift",
          228.344
        ],
        [
          "atomMaxShift",
          235.292
        ],
        [
          "atomDistributionRefValue",
          228.344
        ],
        [
          "atomDistributionValuePerPoint",
          1.0
        ],
        [
          "atomStatisticalDistribution",
          []
        ]
      ],
      [
        [
          "_metadata",
          {
            "jsonVersion": 3.0,
            "className": "AtomChemicalShift",
            "classVersion": 1.0,
            "user": "luca",
            "lastPath": "undefined",
            "timestamp": "Tue Jan  9 15:18:19 2024"
          }
        ],
        [
          "atomName",
          "N9"
        ],
        [
          "atomElementName",
          ""
        ],
        [
          "atomAverageShift",
          150.759
        ],
        [
          "atomStdShift",
          0.077
        ],
        [
          "atomMinShift",
          150.704
        ],
        [
          "atomMaxShift",
          150.813
        ],
        [
          "atomDistributionRefValue",
          150.704
        ],
        [
          "atomDistributionValuePerPoint",
          1.0
        ],
        [
          "atomStatisticalDistribution",
          []
        ]
      ]
    ]
  ]
]